streamdeck_ui/__init__.py
streamdeck_ui/api.py
streamdeck_ui/config.py
streamdeck_ui/dimmer.py
streamdeck_ui/display/__init__.py
streamdeck_ui/display/display_grid.py
streamdeck_ui/display/empty_filter.py
streamdeck_ui/display/filter.py
streamdeck_ui/display/image_filter.py
streamdeck_ui/display/keypress_filter.py
streamdeck_ui/display/pipeline.py
streamdeck_ui/display/pulse_filter.py
streamdeck_ui/display/text_filter.py
streamdeck_ui/fonts/roboto/LICENSE.txt
streamdeck_ui/fonts/roboto/Roboto-Black.ttf
streamdeck_ui/fonts/roboto/Roboto-BlackItalic.ttf
streamdeck_ui/fonts/roboto/Roboto-Bold.ttf
streamdeck_ui/fonts/roboto/Roboto-BoldItalic.ttf
streamdeck_ui/fonts/roboto/Roboto-Italic.ttf
streamdeck_ui/fonts/roboto/Roboto-Light.ttf
streamdeck_ui/fonts/roboto/Roboto-LightItalic.ttf
streamdeck_ui/fonts/roboto/Roboto-Medium.ttf
streamdeck_ui/fonts/roboto/Roboto-MediumItalic.ttf
streamdeck_ui/fonts/roboto/Roboto-Regular.ttf
streamdeck_ui/fonts/roboto/Roboto-Thin.ttf
streamdeck_ui/fonts/roboto/Roboto-ThinItalic.ttf
streamdeck_ui/gui.py
streamdeck_ui/icons/cross.png
streamdeck_ui/icons/gear.png
streamdeck_ui/icons/vertical-align.png
streamdeck_ui/logo.png
streamdeck_ui/main.ui
streamdeck_ui/mock_streamdeck.py
streamdeck_ui/resources.qrc
streamdeck_ui/resources_rc.py
streamdeck_ui/semaphore.py
streamdeck_ui/settings.ui
streamdeck_ui/stream_deck_monitor.py
streamdeck_ui/ui_main.py
streamdeck_ui/ui_settings.py
streamdeck_ui-2.0.15.dist-info/entry_points.txt
streamdeck_ui-2.0.15.dist-info/WHEEL
streamdeck_ui-2.0.15.dist-info/METADATA
streamdeck_ui-2.0.15.dist-info/LICENSE
streamdeck_ui-2.0.15.dist-info/RECORD
